phenopack/__init__.py
phenopack/pack.py
phenopack/analysis/__init__.py
phenopack-0.1.0.dist-info/METADATA
phenopack-0.1.0.dist-info/WHEEL
phenopack-0.1.0.dist-info/RECORD
