Metadata-Version: 2.4
Name: phenopack
Version: 0.1.0
Requires-Python: >=3.9
Requires-Dist: numpy<2,>=1
Provides-Extra: dev
Requires-Dist: ipython; extra == 'dev'
Requires-Dist: jupyterlab; extra == 'dev'
Provides-Extra: lint
Requires-Dist: pre-commit>=2.20.0; extra == 'lint'
Provides-Extra: test
Requires-Dist: pytest<8,>=7; extra == 'test'
